[
  {
    "ScenarioName": "Filter",
    "Description": "Filter \u002B Count with varying selectivity",
    "RowCount": 1000000,
    "Iterations": 5,
    "SamplesMicroseconds": [
      46046.4,
      46065.1,
      45335.9
    ],
    "MinMicroseconds": 45335.9,
    "MaxMicroseconds": 46065.1,
    "MedianMicroseconds": 46046.4,
    "AverageMicroseconds": 45815.799999999996,
    "StdDevMicroseconds": 415.71075280776574,
    "RowsPerSecond": 21717224.36498836,
    "MillionRowsPerSecond": 21.71722436498836,
    "PhaseDetails": null,
    "AllocatedBytes": 37019,
    "Metadata": {
      "HighSelectivity": "Age \u003E 55 -\u003E 199452 rows",
      "LowSelectivity": "IsActive -\u003E 699215 rows",
      "MultiFilter": "Age \u003E 30 \u0026\u0026 IsActive \u0026\u0026 Salary \u003E 50000 -\u003E 466007 rows"
    },
    "Timestamp": "2026-02-06T02:35:18.0629648Z",
    "OutliersRemoved": 2,
    "IsStable": true,
    "StabilityWarning": null
  },
  {
    "ScenarioName": "Aggregate",
    "Description": "Sum, Average, Min, Max aggregations",
    "RowCount": 1000000,
    "Iterations": 5,
    "SamplesMicroseconds": [
      16004.2,
      14859.9,
      15165.2,
      15599.4
    ],
    "MinMicroseconds": 14859.9,
    "MaxMicroseconds": 16004.2,
    "MedianMicroseconds": 15382.3,
    "AverageMicroseconds": 15407.175000000001,
    "StdDevMicroseconds": 500.4834754181869,
    "RowsPerSecond": 65009783.97248786,
    "MillionRowsPerSecond": 65.00978397248785,
    "PhaseDetails": null,
    "AllocatedBytes": 38387,
    "Metadata": {
      "Sum": "115,047,497,862.12",
      "Average": "115,047.50",
      "Min": "30,000.11",
      "Max": "199,999.96"
    },
    "Timestamp": "2026-02-06T02:35:18.8167777Z",
    "OutliersRemoved": 1,
    "IsStable": true,
    "StabilityWarning": null
  },
  {
    "ScenarioName": "SparseAggregation",
    "Description": "Aggregation with varying selection sparsity (1%, 10%, 50%)",
    "RowCount": 1000000,
    "Iterations": 5,
    "SamplesMicroseconds": [
      89022,
      66934.4,
      74437.5,
      68149.7,
      78211.4
    ],
    "MinMicroseconds": 66934.4,
    "MaxMicroseconds": 89022,
    "MedianMicroseconds": 74437.5,
    "AverageMicroseconds": 75351,
    "StdDevMicroseconds": 8924.831772364118,
    "RowsPerSecond": 13434089.00083963,
    "MillionRowsPerSecond": 13.43408900083963,
    "PhaseDetails": null,
    "AllocatedBytes": 195739,
    "Metadata": {
      "1PctSelectivity": "22,112 rows (2.2%), Sum=2,538,683,232.62",
      "10PctSelectivity": "88,543 rows (8.9%), Sum=10,183,164,093.35",
      "50PctSelectivity": "489,243 rows (48.9%), Sum=56,312,271,100.27",
      "100PctSelectivity": "1,000,000 rows, Sum=115,047,497,862.12"
    },
    "Timestamp": "2026-02-06T02:35:19.9127078Z",
    "OutliersRemoved": 0,
    "IsStable": true,
    "StabilityWarning": null
  },
  {
    "ScenarioName": "GroupBy",
    "Description": "GroupBy \u002B aggregations",
    "RowCount": 1000000,
    "Iterations": 5,
    "SamplesMicroseconds": [
      54625.5,
      42749.5,
      42679.8,
      41755.1
    ],
    "MinMicroseconds": 41755.1,
    "MaxMicroseconds": 54625.5,
    "MedianMicroseconds": 42714.65,
    "AverageMicroseconds": 45452.475,
    "StdDevMicroseconds": 6132.1222549103395,
    "RowsPerSecond": 23411171.57696481,
    "MillionRowsPerSecond": 23.41117157696481,
    "PhaseDetails": null,
    "AllocatedBytes": 65233,
    "Metadata": {
      "GroupCount": "20 groups",
      "TotalSalary": "115,047,497,862.12"
    },
    "Timestamp": "2026-02-06T02:35:20.9181191Z",
    "OutliersRemoved": 1,
    "IsStable": true,
    "StabilityWarning": null
  },
  {
    "ScenarioName": "FusedExecution",
    "Description": "Fused filter\u002Baggregate vs separate passes",
    "RowCount": 1000000,
    "Iterations": 5,
    "SamplesMicroseconds": [
      26107.2,
      24011.7,
      22826,
      23244.1
    ],
    "MinMicroseconds": 22826,
    "MaxMicroseconds": 26107.2,
    "MedianMicroseconds": 23627.9,
    "AverageMicroseconds": 24047.25,
    "StdDevMicroseconds": 1458.4420100458806,
    "RowsPerSecond": 42322847.14257298,
    "MillionRowsPerSecond": 42.322847142572975,
    "PhaseDetails": null,
    "AllocatedBytes": 56852,
    "Metadata": {
      "FusedSum": "60,793,615,433.65",
      "MatchCount": "528,216 rows matched"
    },
    "Timestamp": "2026-02-06T02:35:21.7231762Z",
    "OutliersRemoved": 1,
    "IsStable": true,
    "StabilityWarning": null
  },
  {
    "ScenarioName": "ParallelComparison",
    "Description": "Sequential vs parallel execution",
    "RowCount": 1000000,
    "Iterations": 5,
    "SamplesMicroseconds": [
      50850.4,
      49473.8,
      50807.8,
      50069.8
    ],
    "MinMicroseconds": 49473.8,
    "MaxMicroseconds": 50850.4,
    "MedianMicroseconds": 50438.8,
    "AverageMicroseconds": 50300.45,
    "StdDevMicroseconds": 657.368154081105,
    "RowsPerSecond": 19826006.962893642,
    "MillionRowsPerSecond": 19.826006962893644,
    "PhaseDetails": null,
    "AllocatedBytes": 55230,
    "Metadata": {
      "SequentialTime": "33440.7 ?s",
      "ParallelTime": "5796.8 ?s",
      "Speedup": "5.77x",
      "ProcessorCount": "16 cores"
    },
    "Timestamp": "2026-02-06T02:35:22.5630247Z",
    "OutliersRemoved": 1,
    "IsStable": true,
    "StabilityWarning": null
  },
  {
    "ScenarioName": "BitmapOperations",
    "Description": "SelectionBitmap create, popcount, iterate",
    "RowCount": 1000000,
    "Iterations": 5,
    "SamplesMicroseconds": [
      5338.2,
      4594.6,
      1661,
      1880.3,
      1394.5
    ],
    "MinMicroseconds": 1394.5,
    "MaxMicroseconds": 5338.2,
    "MedianMicroseconds": 1880.3,
    "AverageMicroseconds": 2973.72,
    "StdDevMicroseconds": 1845.9925885550028,
    "RowsPerSecond": 531830027.1233314,
    "MillionRowsPerSecond": 531.8300271233314,
    "PhaseDetails": null,
    "AllocatedBytes": 24,
    "Metadata": {
      "CountSet": "666,666",
      "IteratedCount": "666,666",
      "BitmapSize": "122.1 KB",
      "HardwarePopCount": "true",
      "SIMD": "AVX2=True, AVX512=False"
    },
    "Timestamp": "2026-02-06T02:35:23.0671256Z",
    "OutliersRemoved": 0,
    "IsStable": false,
    "StabilityWarning": "High variance detected (CV=62.1%, max/min=3.8x). Consider: more warmup, closing other apps, or using --gc-between-iterations."
  },
  {
    "ScenarioName": "PredicateEvaluation",
    "Description": "Predicate evaluation with SIMD optimization",
    "RowCount": 1000000,
    "Iterations": 5,
    "SamplesMicroseconds": [
      35224.9,
      33143.9,
      30929.2,
      25937.9
    ],
    "MinMicroseconds": 25937.9,
    "MaxMicroseconds": 35224.9,
    "MedianMicroseconds": 32036.550000000003,
    "AverageMicroseconds": 31308.975,
    "StdDevMicroseconds": 3987.2335466878953,
    "RowsPerSecond": 31214347.36262175,
    "MillionRowsPerSecond": 31.21434736262175,
    "PhaseDetails": null,
    "AllocatedBytes": 41524,
    "Metadata": {
      "Int32Match": "533,691 (53.4%)",
      "DoubleMatch": "706,633 (70.7%)",
      "BoolMatch": "699,215 (69.9%)",
      "MultiMatch": "434,907 (43.5%)"
    },
    "Timestamp": "2026-02-06T02:35:23.8150601Z",
    "OutliersRemoved": 1,
    "IsStable": true,
    "StabilityWarning": null
  },
  {
    "ScenarioName": "Enumeration",
    "Description": "Result materialization (ToList, foreach)",
    "RowCount": 1000000,
    "Iterations": 5,
    "SamplesMicroseconds": [
      137121.9,
      143084.8,
      151505,
      129025.7,
      137308.1
    ],
    "MinMicroseconds": 129025.7,
    "MaxMicroseconds": 151505,
    "MedianMicroseconds": 137308.1,
    "AverageMicroseconds": 139609.09999999998,
    "StdDevMicroseconds": 8322.890839425927,
    "RowsPerSecond": 7282891.540994303,
    "MillionRowsPerSecond": 7.282891540994303,
    "PhaseDetails": null,
    "AllocatedBytes": 67490120,
    "Metadata": {
      "ToListCount": "533,691 items",
      "ForeachCount": "310,936 items",
      "FirstId": "0"
    },
    "Timestamp": "2026-02-06T02:35:25.4995268Z",
    "OutliersRemoved": 0,
    "IsStable": true,
    "StabilityWarning": null
  },
  {
    "ScenarioName": "PooledMaterialization",
    "Description": "Pooled vs standard materialization comparison",
    "RowCount": 1000000,
    "Iterations": 5,
    "SamplesMicroseconds": [
      124745.5,
      154560.6,
      148145,
      142805.5,
      91244.7
    ],
    "MinMicroseconds": 91244.7,
    "MaxMicroseconds": 154560.6,
    "MedianMicroseconds": 142805.5,
    "AverageMicroseconds": 132300.25999999998,
    "StdDevMicroseconds": 25492.99901743614,
    "RowsPerSecond": 7002531.415106561,
    "MillionRowsPerSecond": 7.002531415106561,
    "PhaseDetails": null,
    "AllocatedBytes": 59438433,
    "Metadata": {
      "ToArrayPooled_Count": "533,691 items",
      "ToArrayPooled_Allocated": "0 B",
      "ToList_Count": "533,691 items",
      "ToList_Allocated": "0 B",
      "GetIndices_Count": "533,691 items",
      "GetIndices_Allocated": "0 B",
      "Savings_vs_ToList": "N/A"
    },
    "Timestamp": "2026-02-06T02:35:26.9391289Z",
    "OutliersRemoved": 0,
    "IsStable": false,
    "StabilityWarning": "High variance detected (CV=19.3%, max/min=1.7x). Consider: more warmup, closing other apps, or using --gc-between-iterations."
  },
  {
    "ScenarioName": "ShortCircuit",
    "Description": "Any/First operations with early-exit optimization",
    "RowCount": 1000000,
    "Iterations": 5,
    "SamplesMicroseconds": [
      57371.3,
      57341.5,
      57738.1,
      57504.3,
      57804.5
    ],
    "MinMicroseconds": 57341.5,
    "MaxMicroseconds": 57804.5,
    "MedianMicroseconds": 57504.3,
    "AverageMicroseconds": 57551.94,
    "StdDevMicroseconds": 210.72937146966376,
    "RowsPerSecond": 17390003.877970863,
    "MillionRowsPerSecond": 17.390003877970862,
    "PhaseDetails": null,
    "AllocatedBytes": 125025,
    "Metadata": {
      "AnyEarlyMatch": "True",
      "AnyLateMatch": "True",
      "AnyNoMatch": "False",
      "FirstEarlyMatch_Id": "0",
      "FirstOrDefaultNoMatch": "null"
    },
    "Timestamp": "2026-02-06T02:35:27.9273049Z",
    "OutliersRemoved": 0,
    "IsStable": true,
    "StabilityWarning": null
  },
  {
    "ScenarioName": "QueryPlanCache",
    "Description": "Query plan caching performance for repeated queries",
    "RowCount": 1000000,
    "Iterations": 5,
    "SamplesMicroseconds": [
      72092.2,
      72129.2,
      72071
    ],
    "MinMicroseconds": 72071,
    "MaxMicroseconds": 72129.2,
    "MedianMicroseconds": 72092.2,
    "AverageMicroseconds": 72097.46666666666,
    "StdDevMicroseconds": 29.45527683341741,
    "RowsPerSecond": 13871126.141246904,
    "MillionRowsPerSecond": 13.871126141246904,
    "PhaseDetails": null,
    "AllocatedBytes": 299665,
    "Metadata": {
      "CacheHits": "0",
      "CacheMisses": "0",
      "HitRate": "N/A",
      "ColdQueryTime_us": "0.0",
      "WarmQueryTime_us": "0.0",
      "Speedup": "0.0x"
    },
    "Timestamp": "2026-02-06T02:35:28.9163793Z",
    "OutliersRemoved": 2,
    "IsStable": true,
    "StabilityWarning": null
  },
  {
    "ScenarioName": "Pagination",
    "Description": "Take/Skip operations for result set pagination",
    "RowCount": 1000000,
    "Iterations": 5,
    "SamplesMicroseconds": [
      187116.1,
      235423.3,
      187303.7,
      247408.4,
      201637.4
    ],
    "MinMicroseconds": 187116.1,
    "MaxMicroseconds": 247408.4,
    "MedianMicroseconds": 201637.4,
    "AverageMicroseconds": 211777.78000000003,
    "StdDevMicroseconds": 28011.863810125156,
    "RowsPerSecond": 4959397.413376685,
    "MillionRowsPerSecond": 4.959397413376685,
    "PhaseDetails": null,
    "AllocatedBytes": 73132248,
    "Metadata": {},
    "Timestamp": "2026-02-06T02:35:30.9569683Z",
    "OutliersRemoved": 0,
    "IsStable": true,
    "StabilityWarning": null
  },
  {
    "ScenarioName": "NullableColumns",
    "Description": "Null filtering performance with various null distributions",
    "RowCount": 1000000,
    "Iterations": 5,
    "SamplesMicroseconds": [
      355358,
      355087.6,
      355733.9
    ],
    "MinMicroseconds": 355087.6,
    "MaxMicroseconds": 355733.9,
    "MedianMicroseconds": 355358,
    "AverageMicroseconds": 355393.1666666667,
    "StdDevMicroseconds": 324.5819516444936,
    "RowsPerSecond": 2814063.564067785,
    "MillionRowsPerSecond": 2.8140635640677854,
    "PhaseDetails": null,
    "AllocatedBytes": 284286,
    "Metadata": {},
    "Timestamp": "2026-02-06T02:35:34.4263159Z",
    "OutliersRemoved": 2,
    "IsStable": true,
    "StabilityWarning": null
  }
]